analysis/__init__.py
analysis/analytics.py
analysis/visualization.py
transactions/__init__.py
transactions/tracker.py
personal_budget_tracker-0.1.0.dist-info/METADATA
personal_budget_tracker-0.1.0.dist-info/WHEEL
personal_budget_tracker-0.1.0.dist-info/top_level.txt
personal_budget_tracker-0.1.0.dist-info/RECORD
